jupyter_power_usage/__init__.py
jupyter_power_usage/_version.py
jupyter_power_usage/api.py
jupyter_power_usage/config.py
jupyter_power_usage/metrics.py
jupyter_power_usage/utils.py
jupyter_power_usage/etc/jupyter_server_config.d/jupyter-power-usage.json
jupyter_power_usage/tests/__init__.py
jupyter_power_usage/tests/test_basic.py
jupyter_power_usage-1.2.1.data/data/etc/jupyter/jupyter_server_config.d/jupyter-power-usage.json
jupyter_power_usage-1.2.1.data/data/share/jupyter/labextensions/@mahendrapaipuri/jupyter-power-usage/package.json
jupyter_power_usage-1.2.1.data/data/share/jupyter/labextensions/@mahendrapaipuri/jupyter-power-usage/schemas/@mahendrapaipuri/jupyter-power-usage/package.json.orig
jupyter_power_usage-1.2.1.data/data/share/jupyter/labextensions/@mahendrapaipuri/jupyter-power-usage/schemas/@mahendrapaipuri/jupyter-power-usage/plugin.json
jupyter_power_usage-1.2.1.data/data/share/jupyter/labextensions/@mahendrapaipuri/jupyter-power-usage/static/32.12f6430ffa562cbbcb57.js
jupyter_power_usage-1.2.1.data/data/share/jupyter/labextensions/@mahendrapaipuri/jupyter-power-usage/static/646.92e3ed3d9aea0d36c6a9.js
jupyter_power_usage-1.2.1.data/data/share/jupyter/labextensions/@mahendrapaipuri/jupyter-power-usage/static/747.19551df7a36576f1c11f.js
jupyter_power_usage-1.2.1.data/data/share/jupyter/labextensions/@mahendrapaipuri/jupyter-power-usage/static/remoteEntry.9e28434f4d9338b7f3fe.js
jupyter_power_usage-1.2.1.data/data/share/jupyter/labextensions/@mahendrapaipuri/jupyter-power-usage/static/style.js
jupyter_power_usage-1.2.1.data/data/share/jupyter/labextensions/@mahendrapaipuri/jupyter-power-usage/static/third-party-licenses.json
jupyter_power_usage-1.2.1.data/data/share/jupyter/labextensions/@mahendrapaipuri/jupyter-power-usage/install.json
jupyter_power_usage-1.2.1.dist-info/METADATA
jupyter_power_usage-1.2.1.dist-info/WHEEL
jupyter_power_usage-1.2.1.dist-info/licenses/LICENSE
jupyter_power_usage-1.2.1.dist-info/RECORD
