Metadata-Version: 2.4
Name: jupyter_power_usage
Version: 1.2.1
Dynamic: Keywords
Summary: Extension that shows system power usage
Project-URL: Homepage, https://github.com/mahendrapaipuri/jupyter-power-usage
Project-URL: Bug Tracker, https://github.com/mahendrapaipuri/jupyter-power-usage/issues
Project-URL: Repository, https://github.com/mahendrapaipuri/jupyter-power-usage.git
Author-email: Mahendra Paipuri <mahendra.paipuri@cnrs.fr>
License:                                  Apache License
License-File: LICENSE
Classifier: Framework :: Jupyter
Classifier: Framework :: Jupyter :: JupyterLab
Classifier: Framework :: Jupyter :: JupyterLab :: 4
Classifier: Framework :: Jupyter :: JupyterLab :: Extensions
Classifier: Framework :: Jupyter :: JupyterLab :: Extensions :: Prebuilt
Classifier: License :: OSI Approved :: Apache Software License
Classifier: Programming Language :: Python
Classifier: Programming Language :: Python :: 3
Classifier: Programming Language :: Python :: 3.9
Classifier: Programming Language :: Python :: 3.10
Classifier: Programming Language :: Python :: 3.11
Classifier: Programming Language :: Python :: 3.12
Requires-Python: >=3.9
Requires-Dist: jupyterlab<5,>=4.0.0
Requires-Dist: psutil
Requires-Dist: py3nvml
Provides-Extra: dev
Requires-Dist: autopep8; extra == 'dev'
Requires-Dist: black; extra == 'dev'
Requires-Dist: flake8; extra == 'dev'
Requires-Dist: mock; extra == 'dev'
Requires-Dist: pytest; extra == 'dev'
Requires-Dist: pytest-cov>=2.6.1; extra == 'dev'
